pytest_ruff/__init__.py
pytest_ruff/_pytest_compat.py
pytest_ruff-0.4.1.dist-info/LICENSE
pytest_ruff-0.4.1.dist-info/METADATA
pytest_ruff-0.4.1.dist-info/WHEEL
pytest_ruff-0.4.1.dist-info/entry_points.txt
pytest_ruff-0.4.1.dist-info/RECORD
